dbt/adapters/tidb/__init__.py
dbt/adapters/tidb/__version__.py
dbt/adapters/tidb/column.py
dbt/adapters/tidb/connections.py
dbt/adapters/tidb/impl.py
dbt/adapters/tidb/relation.py
dbt/include/tidb/__init__.py
dbt/include/tidb/dbt_project.yml
dbt/include/tidb/sample_profiles.yml
dbt/include/tidb/macros/adapters.sql
dbt/include/tidb/macros/apply_grants.sql
dbt/include/tidb/macros/catalog.sql
dbt/include/tidb/macros/materializations/incremental/helpers.sql
dbt/include/tidb/macros/materializations/incremental/incremental.sql
dbt/include/tidb/macros/materializations/seed/seed.sql
dbt/include/tidb/macros/materializations/snapshot/snapshot.sql
dbt/include/tidb/macros/materializations/snapshot/snapshot_merge.sql
dbt/include/tidb/macros/materializations/snapshot/strategies.sql
dbt/include/tidb/macros/materializations/test/test.sql
dbt/include/tidb/macros/utils/bool_or.sql
dbt/include/tidb/macros/utils/cast_bool_to_text.sql
dbt/include/tidb/macros/utils/date_trunc.sql
dbt/include/tidb/macros/utils/dateadd.sql
dbt/include/tidb/macros/utils/datediff.sql
dbt/include/tidb/macros/utils/hash.sql
dbt/include/tidb/macros/utils/split_part.sql
dbt/include/tidb/macros/utils/timestamps.sql
dbt_tidb-1.6.4.dist-info/LICENSE
dbt_tidb-1.6.4.dist-info/METADATA
dbt_tidb-1.6.4.dist-info/WHEEL
dbt_tidb-1.6.4.dist-info/top_level.txt
dbt_tidb-1.6.4.dist-info/RECORD
