Metadata-Version: 2.1
Name: dbt-tidb
Version: 1.6.4
Summary: The TiDB adapter plugin for dbt
Home-page: https://github.com/pingcap/dbt-tidb.git
Author: daemonxiao
Author-email: qiang.wu@pingcap.com
Classifier: Development Status :: 5 - Production/Stable
Classifier: License :: OSI Approved :: Apache Software License
Classifier: Operating System :: Microsoft :: Windows
Classifier: Operating System :: MacOS :: MacOS X
Classifier: Operating System :: POSIX :: Linux
Classifier: Programming Language :: Python :: 3.8
Classifier: Programming Language :: Python :: 3.9
Classifier: Programming Language :: Python :: 3.10
Classifier: Programming Language :: Python :: 3.11
Requires-Python: >=3.8
License-File: LICENSE
Requires-Dist: dbt-core ~=1.6.4
Requires-Dist: mysql-connector-python <8.2,>=8.0.0
